mb_milvus/src/dim_reduction.py
mb_milvus/src/milvus_extraction.py
mb_milvus/src/version.py
mb_milvus-1.0.202302112246.data/scripts/milvus_search.py
mb_milvus-1.0.202302112246.dist-info/LICENSE
mb_milvus-1.0.202302112246.dist-info/METADATA
mb_milvus-1.0.202302112246.dist-info/WHEEL
mb_milvus-1.0.202302112246.dist-info/top_level.txt
mb_milvus-1.0.202302112246.dist-info/RECORD
